laypy/__init__.py
laypy/py.typed
laypy-0.0.1.dist-info/METADATA
laypy-0.0.1.dist-info/WHEEL
laypy-0.0.1.dist-info/licenses/LICENSE
laypy-0.0.1.dist-info/RECORD
