Metadata-Version: 2.4
Name: laypy
Version: 0.0.1
Summary: Add your description here
Author-email: mert-kurttutan <kurttutan.mert@gmail.com>
License-File: LICENSE
Requires-Python: >=3.9
